{
    "post": [
        {
            "id": 0,
            "contenido": "<p><img style='display: block; margin-left: auto; margin-right: auto;' src='http:\/\/www.gambarnaruto.com\/wp-content\/uploads\/2015\/06\/25+gambar+uchiha+madara+terlengkap+16.jpg' alt='' width='1085' height='610' \/><\/p><p style='text-align: center;'><img src='https:\/\/kr.best-wallpaper.net\/wallpaper\/1366x768\/1407\/Naruto-two-boys_1366x768.jpg' \/><\/p><p style='text-align: center;'><img src='http:\/\/www.gw-micro.com\/wp-content\/uploads\/2016\/11\/Madara-Uchiha-Naruto-Anime-Obito-Tobi-Akatsuki-Naruto-Madara-Naruto-Tobi-Obito-Uzumaki-Naruto-Hashirama-Senju-Nice-Desktop-Wallpaper-892236hd-1366x768.jpg' \/><\/p><p style='text-align: center;'><img src='http:\/\/s1.picswalls.com\/wallpapers\/2015\/09\/27\/hd-naruto-wallpaper_104041490_274.jpg' \/><\/p><p style='text-align: center;'><img src='https:\/\/wallpaperscraft.com\/image\/naruto_shippuden_ultimate_ninja_storm_4_2016_107108_1366x768.jpg' \/><\/p><p style='text-align: center;'><img src='https:\/\/images8.alphacoders.com\/505\/505025.jpg' \/><\/p><p style='text-align: center;'><img src='http:\/\/www.themeraider.com\/wp-content\/uploads\/2016\/03\/naruto-battlefield-feat.jpg' \/><\/p><p style='text-align: center;'><img src='http:\/\/k33.kn3.net\/taringa\/F\/4\/D\/2\/B\/1\/War841\/F8C.jpg' \/><\/p>",
            "url": "naruto",
            "datos": {
                "titulo": "Imagenes de Naruto",
                "descripcion": "Pack de Imagenes de Naruto",
                "portada": "http:\/\/s1.picswalls.com\/wallpapers\/2015\/09\/27\/hd-naruto-wallpaper_104041490_274.jpg",
                "autor": "AngelKrak"
            },
            "fecha": {
                "dia": "22",
                "mes": "Febrero",
                "completa": "Miércoles 22 de Febrero de 2017",
                "hora_publicacion": "12:28:01 AM"
            },
            "info": {
                "destacado": "no",
                "tags": "Naruto, Wallpapers, Imagenes, Imagenes de Naruto, Naruto Shippuden",
                "categoria": "Imagenes",
                "imagen": "http:\/\/s33.postimg.org\/u99hgsi65\/1_AE_1.jpg"
            }
        }
    ]
}